git_uff/config.py
git_uff/converters.py
git_uff/main.py
git_uff-0.4.0.dist-info/LICENSE
git_uff-0.4.0.dist-info/METADATA
git_uff-0.4.0.dist-info/WHEEL
git_uff-0.4.0.dist-info/entry_points.txt
git_uff-0.4.0.dist-info/RECORD
