Metadata-Version: 2.3
Name: git-uff
Version: 0.4.0
Summary: Prints the forge url for a given file of a Git repository checkout
License: Apache 2.0
Author: Aurélien Gâteau
Author-email: mail@agateau.com
Requires-Python: >=3.6,<4.0
Classifier: Development Status :: 4 - Beta
Classifier: Environment :: Console
Classifier: Intended Audience :: Developers
Classifier: License :: Other/Proprietary License
Classifier: Programming Language :: Python :: 3
Classifier: Programming Language :: Python :: 3.6
Classifier: Programming Language :: Python :: 3.7
Classifier: Programming Language :: Python :: 3.8
Classifier: Programming Language :: Python :: 3.9
Classifier: Programming Language :: Python :: 3.10
Classifier: Programming Language :: Python :: 3.11
Classifier: Programming Language :: Python :: 3.12
Classifier: Programming Language :: Python :: 3.13
Requires-Dist: gitpython (>=3.1.12,<4.0.0)
Requires-Dist: pyperclip (>=1.8.2,<2.0.0)
Project-URL: Homepage, https://github.com/agateau/git-uff
Project-URL: Repository, https://github.com/agateau/git-uff
